serializer_pkg/__init__.py
serializer_pkg/serializer.py
serializer_pkg_ilyaLihota-0.0.1.dist-info/LICENSE
serializer_pkg_ilyaLihota-0.0.1.dist-info/METADATA
serializer_pkg_ilyaLihota-0.0.1.dist-info/WHEEL
serializer_pkg_ilyaLihota-0.0.1.dist-info/top_level.txt
serializer_pkg_ilyaLihota-0.0.1.dist-info/RECORD
