Metadata-Version: 2.1
Name: serializer-pkg-ilyaLihota
Version: 0.0.1
Summary: Serializer/deserializer program.
Home-page: https://github.com/pypa/sampleproject
Author: Ilya Likhota
Author-email: lihota2020@gmail.com
License: UNKNOWN
Platform: UNKNOWN
Classifier: Programming Language :: Python :: 3
Classifier: License :: OSI Approved :: MIT License
Classifier: Operating System :: OS Independent
Requires-Python: >=3.6
